README.rst
setup.py
libfaketime_tz_wrapper/__init__.py
libfaketime_tz_wrapper/_version.py
libfaketime_tz_wrapper.egg-info/PKG-INFO
libfaketime_tz_wrapper.egg-info/SOURCES.txt
libfaketime_tz_wrapper.egg-info/dependency_links.txt
libfaketime_tz_wrapper.egg-info/not-zip-safe
libfaketime_tz_wrapper.egg-info/requires.txt
libfaketime_tz_wrapper.egg-info/top_level.txt