Metadata-Version: 1.1
Name: libfaketime-tz-wrapper
Version: 1.1.0
Summary: A wrapper around python-libfaketime that introduces timezone-awareness.
Home-page: https://github.com/jppgks/python-libfaketime-tz-wrapper
Author: Joppe Geluykens and Roeland Matthijssens
Author-email: joppe@youngwolves.co
License: GPLv2
Download-URL: https://github.com/jppgks/python-libfaketime-tz-wrapper/tarball/1.1.0
Platform: UNKNOWN
Classifier: License :: OSI Approved :: GNU General Public License v2 (GPLv2)
Classifier: Development Status :: 4 - Beta
Classifier: Intended Audience :: Developers
Classifier: Operating System :: OS Independent
Classifier: Programming Language :: Python
Classifier: Programming Language :: Python :: 2.7
Classifier: Topic :: Software Development :: Libraries :: Python Modules
